drover/__init__.py
drover/_copy_patch.py
drover/cli.py
drover/io.py
drover/models.py
drover-0.7.1.dist-info/LICENSE
drover-0.7.1.dist-info/METADATA
drover-0.7.1.dist-info/WHEEL
drover-0.7.1.dist-info/entry_points.txt
drover-0.7.1.dist-info/top_level.txt
drover-0.7.1.dist-info/RECORD
