Metadata-Version: 2.1
Name: drover
Version: 0.7.1
Summary: a command-line utility to deploy Python packages to Lambda functions
Home-page: https://github.com/jwilges/drover
Author: Jeffrey Wilges
Author-email: jeffrey@wilges.com
License: BSD
Platform: UNKNOWN
Classifier: Development Status :: 4 - Beta
Classifier: Operating System :: POSIX :: Linux
Classifier: Operating System :: MacOS :: MacOS X
Classifier: Programming Language :: Python :: 3.6
Classifier: Programming Language :: Python :: 3.7
Classifier: Programming Language :: Python :: 3.8
Classifier: Environment :: Console
Classifier: Topic :: Software Development :: Build Tools
Classifier: Topic :: System :: Distributed Computing
Classifier: Topic :: System :: Networking
Classifier: Topic :: System :: Software Distribution
Classifier: Topic :: Utilities
Requires-Python: >=3.6
Requires-Dist: boto3 (>=1.12)
Requires-Dist: botocore (>=1.15)
Requires-Dist: pydantic (>=1.4)
Requires-Dist: pyyaml (>=5.3)
Requires-Dist: tqdm (>=4.44)
Requires-Dist: dataclasses ; python_version < "3.7"
